[
    {
        "id": 1,
        "image": "popular/2.jpg",
        "title": "Гостиная Джоконда (крем)",
        "price": "18 000",
        "oldPrice": "72 440"
    },
    {
        "id": 2,
        "image": "popular/8.jpg",
        "title": "Малая гостиная Матильда",
        "price": "186 700",
        "oldPrice": "226 400"
    },
    {
        "id": 3,
        "image": "popular/3.jpg",
        "title": "Спальня Элиза Люкс c 5дверным шкафом (крем)",
        "price": "59 800",
        "oldPrice": "139 500"
    },
    {
        "id": 4,
        "image": "popular/12.jpg",
        "title": "Модульная система для спальни Тиффани (штрих /золото)",
        "price": "95 500",
        "oldPrice": "173 000"
    },
    {
        "id": 5,
        "image": "popular/1.jpg",
        "title": "Гостиная Джоконда (крем)",
        "price": "18 000",
        "oldPrice": "72 440"
    },
    {
        "id": 6,
        "image": "popular/7.jpg",
        "title": "Малая гостиная Матильда",
        "price": "186 700",
        "oldPrice": "226 400"
    },
    {
        "id": 7,
        "image": "popular/6.jpg",
        "title": "Спальня Элиза Люкс c 5дверным шкафом (крем)",
        "price": "59 800",
        "oldPrice": "139 500"
    },
    {
        "id": 8,
        "image": "popular/10.jpg",
        "title": "Модульная система для спальни Тиффани (штрих /золото)",
        "price": "95 500",
        "oldPrice": "173 000"
    }
]